omniblack/moneta/__init__.py
omniblack/moneta/app.py
omniblack/moneta/changes.py
omniblack/moneta/diff.tcss
omniblack/moneta/display.py
omniblack/moneta/display_diff.py
omniblack/moneta/install.py
omniblack/moneta/message_explainer.txt
omniblack/moneta/parse_diff.py
omniblack/moneta/publish.py
omniblack/moneta/read_change.py
omniblack/moneta/severity_explainer.txt
omniblack/moneta/yaml.py
omniblack.moneta-0.0.6.dist-info/LICENSE.txt
omniblack.moneta-0.0.6.dist-info/METADATA
omniblack.moneta-0.0.6.dist-info/WHEEL
omniblack.moneta-0.0.6.dist-info/entry_points.txt
omniblack.moneta-0.0.6.dist-info/top_level.txt
omniblack.moneta-0.0.6.dist-info/RECORD
