Metadata-Version: 2.1
Name: omniblack.moneta
Version: 0.0.6
Summary: A changelog manager for omniblack.
Author-email: Terry Patterson <Terryp@wegrok.net>
License: 
Project-URL: Homepage, https://gitlab.com/terryp/terry/-/tree/next/tooling/moneta
Project-URL: Repository, https://gitlab.com/terryp/terry.git
Requires-Python: ~=3.9
License-File: LICENSE.txt
Requires-Dist: attrs ~=23.2
Requires-Dist: more-itertools ~=10.2
Requires-Dist: atpublic ~=4.0
Requires-Dist: ruamel.yaml ~=0.18
Requires-Dist: sh ~=2.0
Requires-Dist: textual ~=0.47
Requires-Dist: omniblack.cli
Requires-Dist: omniblack.model
Requires-Dist: omniblack.repo
